cdk_stack_parameters_shared_via_ssm/__init__.py
cdk_stack_parameters_shared_via_ssm/py.typed
cdk_stack_parameters_shared_via_ssm/_jsii/__init__.py
cdk_stack_parameters_shared_via_ssm/_jsii/cdk-stack-parameters-shared-via-ssm@0.1.3.jsii.tgz
cdk_stack_parameters_shared_via_ssm-0.1.3.dist-info/LICENSE
cdk_stack_parameters_shared_via_ssm-0.1.3.dist-info/METADATA
cdk_stack_parameters_shared_via_ssm-0.1.3.dist-info/WHEEL
cdk_stack_parameters_shared_via_ssm-0.1.3.dist-info/top_level.txt
cdk_stack_parameters_shared_via_ssm-0.1.3.dist-info/RECORD
