Metadata-Version: 2.1
Name: cdk-stack-parameters-shared-via-ssm
Version: 0.1.3
Summary: cdk-stack-parameters-shared-via-ssm
Home-page: https://github.com/delplace.vivian/cdk-stack-parameters-shared-via-ssm.git
Author: viviandelplace<delplace.vivian@gmail.com>
License: Apache-2.0
Project-URL: Source, https://github.com/delplace.vivian/cdk-stack-parameters-shared-via-ssm.git
Platform: UNKNOWN
Classifier: Intended Audience :: Developers
Classifier: Operating System :: OS Independent
Classifier: Programming Language :: JavaScript
Classifier: Programming Language :: Python :: 3 :: Only
Classifier: Programming Language :: Python :: 3.6
Classifier: Programming Language :: Python :: 3.7
Classifier: Programming Language :: Python :: 3.8
Classifier: Programming Language :: Python :: 3.9
Classifier: Typing :: Typed
Classifier: Development Status :: 5 - Production/Stable
Classifier: License :: OSI Approved
Requires-Python: >=3.6
Requires-Dist: aws-cdk.aws-lambda (<2.0.0,>=1.95.2)
Requires-Dist: aws-cdk.core (<2.0.0,>=1.95.2)
Requires-Dist: constructs (<4.0.0,>=3.2.27)
Requires-Dist: jsii (<2.0.0,>=1.29.0)
Requires-Dist: publication (>=0.0.3)
